<doors>
	<door id="doorLabyrinthRoom">
		<scene>game.scenes.myth.labyrinthRoom.LabyrinthRoom</scene>
		<x>485</x>
		<y>524</y>
		<label>
			<text>Exit</text>
			<type>exit3D</type>
			<offset>
				<x>0</x>
				<y>0</y>
			</offset>
		</label>
	</door>
	<door id="doorLabyrinthSnake">
		<scene>game.scenes.myth.labyrinthSnake.LabyrinthSnake</scene>
		<x>278</x>
		<y>574</y>
		<label>
			<text>Exit</text>
			<type>exit3D</type>
			<offset>
				<x>0</x>
				<y>0</y>
			</offset>
		</label>
	</door>
</doors>