<npcs>
	<npc id="masterCoin">
		<skin>
			<gender>male</gender>
			<skinColor>0xd2aa72</skinColor>
			<hairColor>0x0</hairColor>
			<mouth>hercules</mouth>
			<marks>an2_coin</marks>
			<facial>an2_coin</facial>
			<hair>an2_coin</hair>
			<shirt>an2_coin</shirt>
			<pants>an_sultan</pants>
			<overpants>an2_coin</overpants>
			<eyeState>squint</eyeState>
		</skin>
		<position>
			<x>1500</x>
			<y>737</y>
		</position>
		<range>
			<x>0</x>
			<y>0</y>
		</range>
		<faceSpeaker>false</faceSpeaker>
		<direction>right</direction>
	</npc>
	<npc id="masterThief">
		<skin>
			<gender>male</gender>
			<skinColor>0xd2aa72</skinColor>
			<hairColor>0x0</hairColor>
			<mouth>fortuneHunter</mouth>
			<marks>an2_master</marks>
			<facial>an2_master</facial>
			<hair>an2_master</hair>
			<shirt>an2_master</shirt>
			<pants>an2_master</pants>
			<pack>an2_master</pack>
			<overshirt>an2_master</overshirt>
			<overpants>an2_master</overpants>
			<eyeState>squint</eyeState>
		</skin>
		<position>
			<x>1750</x>
			<y>737</y>
		</position>
		<range>
			<x>0</x>
			<y>0</y>
		</range>
		<faceSpeaker>false</faceSpeaker>
		<direction>right</direction>
	</npc>
	<npc id="jailer">
		<skin>
			<gender>male</gender>
			<skinColor>0xd2aa72</skinColor>
			<hairColor>0x69665c</hairColor>
			<mouth>prisoner3</mouth>
			<marks>an2_jailer</marks>
			<facial>an2_jailer</facial>
			<hair>an2_jailer</hair>
			<shirt>an_thief2</shirt>
			<pants>an_thief2</pants>
			<pack>an_thief1</pack>
			<item>an2_jailer</item>
			<overshirt>an_thief1</overshirt>
			<overpants>an2_jailer</overpants>
			<eyeState>squint</eyeState>
		</skin>
		<position>
			<x>1610</x>
			<y>737</y>
		</position>
		<range>
			<x>0</x>
			<y>0</y>
		</range>
		<faceSpeaker>false</faceSpeaker>
		<direction>right</direction>
	</npc>
	<npc id="enforcer">
		<skin>
			<gender>male</gender>
			<skinColor>0xd2aa72</skinColor>
			<hairColor>0x0</hairColor>
			<mouth>MTHscaredSumo</mouth>
			<marks>an2_enforcer</marks>
			<hair>an2_enforcer</hair>
			<shirt>1</shirt>
			<pants>an_townie3</pants>
			<overpants>an2_enforcer</overpants>
			<eyeState>squint</eyeState>
		</skin>
		<position>
			<x>1680</x>
			<y>580</y>
		</position>
		<range>
			<x>0</x>
			<y>0</y>
		</range>
		<faceSpeaker>false</faceSpeaker>
		<direction>right</direction>
		<scale>.43</scale>
	</npc>
	<npc id="prisoner">
		<skin>
			<gender>male</gender>
			<skinColor>0xd2aa72</skinColor>
			<hairColor>0x0</hairColor>
			<mouth>5</mouth>
			<marks>bags</marks>
			<facial>an2_prisoner</facial>
			<hair>1</hair>
			<shirt>1</shirt>
			<pants>1</pants>
			<item>empty</item>
			<overshirt>an2_prisoner</overshirt>
			<eyeState>squint</eyeState>
		</skin>
		<position>
			<x>1862</x>
			<y>580</y>
		</position>
		<range>
			<x>0</x>
			<y>0</y>
		</range>
		<faceSpeaker>false</faceSpeaker>
		<direction>left</direction>
	</npc>
	<npc id="vizier">
		<skin>
			<gender>male</gender>
			<skinColor>0xd2aa72</skinColor>
			<hairColor>0x999999</hairColor>
			<mouth>astroking</mouth>
			<marks>an_brokemerch</marks>
			<hair>an2_vizier</hair>
			<shirt>an2_vizier</shirt>
			<pants>an2_vizier</pants>
			<item>empty</item>
			<overpants>an2_vizier</overpants>
			<eyeState>squint</eyeState>
		</skin>
		<position>
			<x>100</x>
			<y>1100</y>
		</position>
		<range>
			<x>0</x>
			<y>0</y>
		</range>
		<direction>left</direction>
	</npc>
</npcs>